multicorn/__init__.py
multicorn/__main__.py
multicorn-0.1.0.dist-info/LICENSE
multicorn-0.1.0.dist-info/WHEEL
multicorn-0.1.0.dist-info/METADATA
multicorn-0.1.0.dist-info/RECORD
