Metadata-Version: 2.1
Name: multicorn
Version: 0.1.0
Summary: 
License: MIT
Author: An Long
Author-email: aisk1988@gmail.com
Requires-Python: >=3.8,<4.0
Classifier: License :: OSI Approved :: MIT License
Classifier: Programming Language :: Python :: 3
Classifier: Programming Language :: Python :: 3.8
Requires-Dist: backports.interpreters (>=0.1.0,<0.2.0)
